funman_dreal/__init__.py
funman_dreal/_version.py
funman_dreal/converter.py
funman_dreal/solver.py
funman_dreal/example/__init__.py
funman_dreal-1.5.0.dist-info/METADATA
funman_dreal-1.5.0.dist-info/WHEEL
funman_dreal-1.5.0.dist-info/top_level.txt
funman_dreal-1.5.0.dist-info/RECORD
